{
    "product":  {
                    "wiringPdf":  "assets/docs/wiring/wiring.pdf",
                    "description":  "Product folder ETX-2I-10G 12SFP-12UTP-PTP",
                    "videos":  [

                               ],
                    "images":  [
                                   "assets/images/1.jpg",
                                   "assets/images/2.png"
                               ],
                    "name":  "ETX-2I-10G 12SFP-12UTP-PTP",
                    "drawingPdf":  "assets/docs/drawing.pdf"
                }
}